EmailSender/__init__.py
EmailSender/config.py
EmailSender/sender.py
EmailSenderVaryTest/__init__.py
EmailSenderVaryTest/config.py
EmailSenderVaryTest/sender.py
EmailSenderVaryTest-1.0.0.dist-info/LICENSE.txt
EmailSenderVaryTest-1.0.0.dist-info/METADATA
EmailSenderVaryTest-1.0.0.dist-info/WHEEL
EmailSenderVaryTest-1.0.0.dist-info/top_level.txt
EmailSenderVaryTest-1.0.0.dist-info/RECORD
